xcomfort/__init__.py
xcomfort/bridge.py
xcomfort/comp.py
xcomfort/connection.py
xcomfort/devices.py
xcomfort/messages.py
xcomfort/room.py
xcomfort-0.1.0.dist-info/LICENSE
xcomfort-0.1.0.dist-info/METADATA
xcomfort-0.1.0.dist-info/WHEEL
xcomfort-0.1.0.dist-info/top_level.txt
xcomfort-0.1.0.dist-info/RECORD
