Metadata-Version: 2.1
Name: xcomfort
Version: 0.1.0
Summary: Integration with Eaton xComfort Bridge
Home-page: https://github.com/jankrib/xcomfort-python
Author: Jan Kristian Bjerke
Author-email: jan.bjerke@gmail.com
Classifier: Programming Language :: Python :: 3
Classifier: License :: OSI Approved :: MIT License
Classifier: Operating System :: OS Independent
Classifier: Development Status :: 2 - Pre-Alpha
Requires-Python: >=3.7
License-File: LICENSE
Requires-Dist: aiohttp
Requires-Dist: rx
Requires-Dist: pycryptodome
